{"429010":{"success":true,"data":{"type":"dlc","name":"The Secret World: Issue 6 - The Last Train To Cairo","steam_appid":429010,"required_age":"17","is_free":false,"detailed_description":"Issue #6: The Last Train to Cairo sends you to strike at the heart of the Cult of Aten\u2019s plots in Egypt.   Includes new missions and access to the Whip Auxiliary Weapon.","about_the_game":"Issue #6: The Last Train to Cairo sends you to strike at the heart of the Cult of Aten\u2019s plots in Egypt.   Includes new missions and access to the Whip Auxiliary Weapon.","short_description":"Issue #6: The Last Train to Cairo sends you to strike at the heart of the Cult of Aten\u2019s plots in Egypt.   Includes new missions and access to the Whip Auxiliary Weapon.","fullgame":{"appid":"215280","name":"Secret World Legends"},"supported_languages":"English<strong>*<\/strong>, French<strong>*<\/strong>, German<strong>*<\/strong><br><strong>*<\/strong>languages with full audio support","header_image":"https:\/\/steamcdn-a.akamaihd.net\/steam\/apps\/429010\/header.jpg?t=1473360261","website":"http:\/\/www.thesecretworld.com","pc_requirements":{"minimum":"<strong>Minimum:<\/strong><br><ul class=\"bb_ul\"><li><strong>OS:<\/strong> Windows XP (SP 1) \/ Vista (SP 1) \/ Windows 7 (SP 1)<br>\t<\/li><li><strong>Processor:<\/strong> 2.6 GHZ Intel Core 2 DUO or equivalent AMD CPU<br>\t<\/li><li><strong>Memory:<\/strong> At least 2GB RAM for Windows XP \/ 3GB Ram for Windows Vista and Windows 7<br>\t<\/li><li><strong>Hard Disk Space:<\/strong> At least 30GB of free space<br>\t<\/li><li><strong>Video Card:<\/strong> nVidia 8800 series 512 VRAM or better\/Radeon HD3850 512MB or better<br>\t<\/li><li><strong>DirectX\u00ae:<\/strong> 9.0c<br>\t<\/li><li><strong>Sound:<\/strong> DirectX 9.0c compatible sound card<br>\t<\/li><li><strong>Additional:<\/strong> Requires account registration (free) with the developer. 30 days of free Membership is included.<\/li><\/ul>","recommended":"<strong>Recommended:<\/strong><br><ul class=\"bb_ul\"><li><strong>OS:<\/strong> Windows 7 64 bit is highly-recommended<br>\t<\/li><li><strong>Processor:<\/strong> Intel Core i5 3.0Ghz or equivalent<br>\t<\/li><li><strong>Memory:<\/strong> 6GB<br>\t<\/li><li><strong>Hard Disk Space:<\/strong> At least 30GB of free space<br>\t<\/li><li><strong>Video Card:<\/strong> Nvidia GTX 560 Ti 1Gb<br>\t<\/li><li><strong>DirectX\u00ae:<\/strong> 11.0<br>\t<\/li><li><strong>Sound:<\/strong> DirectX 9.0c compatible sound card<br>\t<\/li><li><strong>Additional:<\/strong> Requires account registration (free) with the developer. 30 days of free Membership is included.<\/li><\/ul>"},"mac_requirements":[],"linux_requirements":[],"developers":["Funcom"],"publishers":[""],"package_groups":[],"platforms":{"windows":true,"mac":false,"linux":false},"categories":[{"id":1,"description":"Multi-player"},{"id":20,"description":"MMO"},{"id":9,"description":"Co-op"},{"id":21,"description":"Downloadable Content"},{"id":29,"description":"Steam Trading Cards"}],"genres":[{"id":"25","description":"Adventure"},{"id":"29","description":"Massively Multiplayer"},{"id":"3","description":"RPG"}],"screenshots":[{"id":0,"path_thumbnail":"https:\/\/steamcdn-a.akamaihd.net\/steam\/apps\/429010\/ss_228409d7f7233a5a613ca16d0d792847b4daa3dd.600x338.jpg?t=1473360261","path_full":"https:\/\/steamcdn-a.akamaihd.net\/steam\/apps\/429010\/ss_228409d7f7233a5a613ca16d0d792847b4daa3dd.1920x1080.jpg?t=1473360261"},{"id":1,"path_thumbnail":"https:\/\/steamcdn-a.akamaihd.net\/steam\/apps\/429010\/ss_a9e055ebbe89e0e89695d90cb7277377863ed6bd.600x338.jpg?t=1473360261","path_full":"https:\/\/steamcdn-a.akamaihd.net\/steam\/apps\/429010\/ss_a9e055ebbe89e0e89695d90cb7277377863ed6bd.1920x1080.jpg?t=1473360261"},{"id":2,"path_thumbnail":"https:\/\/steamcdn-a.akamaihd.net\/steam\/apps\/429010\/ss_3c9a0b83c6c9da9b507632b6a28a9a21b29c6a02.600x338.jpg?t=1473360261","path_full":"https:\/\/steamcdn-a.akamaihd.net\/steam\/apps\/429010\/ss_3c9a0b83c6c9da9b507632b6a28a9a21b29c6a02.1920x1080.jpg?t=1473360261"},{"id":3,"path_thumbnail":"https:\/\/steamcdn-a.akamaihd.net\/steam\/apps\/429010\/ss_123d08e408011d4f21bae1c048c3537853e02c96.600x338.jpg?t=1473360261","path_full":"https:\/\/steamcdn-a.akamaihd.net\/steam\/apps\/429010\/ss_123d08e408011d4f21bae1c048c3537853e02c96.1920x1080.jpg?t=1473360261"},{"id":4,"path_thumbnail":"https:\/\/steamcdn-a.akamaihd.net\/steam\/apps\/429010\/ss_dec105c20b0273ec903a49adc0615c5c7886e958.600x338.jpg?t=1473360261","path_full":"https:\/\/steamcdn-a.akamaihd.net\/steam\/apps\/429010\/ss_dec105c20b0273ec903a49adc0615c5c7886e958.1920x1080.jpg?t=1473360261"}],"movies":[{"id":256670262,"name":"Issue 6","thumbnail":"https:\/\/steamcdn-a.akamaihd.net\/steam\/apps\/256670262\/movie.293x165.jpg?t=1473360251","webm":{"480":"http:\/\/steamcdn-a.akamaihd.net\/steam\/apps\/256670262\/movie480.webm?t=1473360251","max":"http:\/\/steamcdn-a.akamaihd.net\/steam\/apps\/256670262\/movie_max.webm?t=1473360251"},"highlight":true}],"release_date":{"coming_soon":false,"date":"Sep 8, 2016"},"support_info":{"url":"http:\/\/help.funcom.com\/","email":""},"background":"https:\/\/steamcdn-a.akamaihd.net\/steam\/apps\/429010\/page_bg_generated_v6b.jpg?t=1473360261"}}}