{"599110":{"success":true,"data":{"type":"demo","name":"LightVR Demo","steam_appid":599110,"required_age":0,"is_free":true,"detailed_description":"This is the full VR Toolbox experience, except for:<br \/>\r\n<br \/>\r\n1. A watermark at the top third of the view.<br \/>\r\n2. No FXAA\/MSAA and image post-processing support.","about_the_game":"This is the full VR Toolbox experience, except for:<br \/>\r\n<br \/>\r\n1. A watermark at the top third of the view.<br \/>\r\n2. No FXAA\/MSAA and image post-processing support.","short_description":"Try VR Toolbox for free.","fullgame":{"appid":"488040","name":"VR Toolbox"},"supported_languages":"English","header_image":"https:\/\/steamcdn-a.akamaihd.net\/steam\/apps\/599110\/header.jpg?t=1490393427","website":"http:\/\/www.vr-toolbox.com","pc_requirements":[],"mac_requirements":[],"linux_requirements":[],"developers":["MyDream Interactive Inc."],"publishers":["MyDream Interactive Inc."],"package_groups":[],"platforms":{"windows":true,"mac":false,"linux":false},"categories":[{"id":10,"description":"Game demo"}],"genres":[{"id":"51","description":"Animation & Modeling"},{"id":"57","description":"Utilities"}],"screenshots":[{"id":0,"path_thumbnail":"https:\/\/steamcdn-a.akamaihd.net\/steam\/apps\/599110\/ss_78e1ad9527ef2cb52a3cb7797fe9f841eea9c127.600x338.jpg?t=1490393427","path_full":"https:\/\/steamcdn-a.akamaihd.net\/steam\/apps\/599110\/ss_78e1ad9527ef2cb52a3cb7797fe9f841eea9c127.1920x1080.jpg?t=1490393427"},{"id":1,"path_thumbnail":"https:\/\/steamcdn-a.akamaihd.net\/steam\/apps\/599110\/ss_986cfe7c24b2a0ae5888ec96bf573ea8e21707e1.600x338.jpg?t=1490393427","path_full":"https:\/\/steamcdn-a.akamaihd.net\/steam\/apps\/599110\/ss_986cfe7c24b2a0ae5888ec96bf573ea8e21707e1.1920x1080.jpg?t=1490393427"},{"id":2,"path_thumbnail":"https:\/\/steamcdn-a.akamaihd.net\/steam\/apps\/599110\/ss_a927e079881ab225ca98623339f31dbcb03fba7b.600x338.jpg?t=1490393427","path_full":"https:\/\/steamcdn-a.akamaihd.net\/steam\/apps\/599110\/ss_a927e079881ab225ca98623339f31dbcb03fba7b.1920x1080.jpg?t=1490393427"},{"id":3,"path_thumbnail":"https:\/\/steamcdn-a.akamaihd.net\/steam\/apps\/599110\/ss_233f5e3bbfdce4c7914f381a97a5f1cf8b4ff375.600x338.jpg?t=1490393427","path_full":"https:\/\/steamcdn-a.akamaihd.net\/steam\/apps\/599110\/ss_233f5e3bbfdce4c7914f381a97a5f1cf8b4ff375.1920x1080.jpg?t=1490393427"},{"id":4,"path_thumbnail":"https:\/\/steamcdn-a.akamaihd.net\/steam\/apps\/599110\/ss_2fae00b966a2ad9bbc2e5eacab1a525422ea413a.600x338.jpg?t=1490393427","path_full":"https:\/\/steamcdn-a.akamaihd.net\/steam\/apps\/599110\/ss_2fae00b966a2ad9bbc2e5eacab1a525422ea413a.1920x1080.jpg?t=1490393427"}],"release_date":{"coming_soon":false,"date":"Mar 24, 2017"},"support_info":{"url":"","email":"support@mydreaminteractive.com"},"background":"https:\/\/steamcdn-a.akamaihd.net\/steam\/apps\/599110\/page_bg_generated_v6b.jpg?t=1490393427"}}}