{"624460":{"success":true,"data":{"type":"game","name":"Fantasynth","steam_appid":624460,"required_age":0,"is_free":true,"detailed_description":"Fantasynth is an audio-reactive experience designed for Virtual Reality.<br \/>\r\n<br \/>\r\nGlide through a procedurally populated environment that comes alight with the music.<br \/>\r\n<br \/>\r\nFeaturing the song Chez Nous by N'to.<br \/>\r\n<br \/>\r\nDuration: 7 minutes.","about_the_game":"Fantasynth is an audio-reactive experience designed for Virtual Reality.<br \/>\r\n<br \/>\r\nGlide through a procedurally populated environment that comes alight with the music.<br \/>\r\n<br \/>\r\nFeaturing the song Chez Nous by N'to.<br \/>\r\n<br \/>\r\nDuration: 7 minutes.","short_description":"Fantasynth is an audio-reactive experience designed for Virtual Reality and lasting 7 minutes.<br \/>\r\n<br \/>\r\nGlide through a procedurally populated environment that comes alight with the music.<br \/>\r\n<br \/>\r\nFeaturing the song Chez Nous by N'to.","supported_languages":"English","reviews":"\u201cAn infectiously cool ride through mind-bending geometry\u201d<br><a href=\"https:\/\/steamcommunity.com\/linkfilter\/?url=http:\/\/www.roadtovr.com\/fantasynth-alpha-preview\/\" target=\"_blank\" rel=\"noopener\"  >Road to VR<\/a><br>","header_image":"https:\/\/steamcdn-a.akamaihd.net\/steam\/apps\/624460\/header.jpg?t=1494604209","website":"http:\/\/fantasynth.com","pc_requirements":{"minimum":"<strong>Minimum:<\/strong><br><ul class=\"bb_ul\"><li><strong>OS:<\/strong> Windows 7 SP1, Windows 8.1 or later, Windows 10<br><\/li><li><strong>Processor:<\/strong> Intel\u00ae i5-4590 \/ AMD FX 8350 equivalent or greater<br><\/li><li><strong>Memory:<\/strong> 4 GB RAM<br><\/li><li><strong>Graphics:<\/strong> NVIDIA GeForce\u00ae GTX 970 \/ AMD Radeon\u2122 R9 290 equivalent or greater<br><\/li><li><strong>DirectX:<\/strong> Version 11<br><\/li><li><strong>Storage:<\/strong> 512 MB available space<\/li><\/ul>"},"mac_requirements":[],"linux_requirements":[],"legal_notice":"Copyright 2017 HelloEnjoy","developers":["HelloEnjoy"],"publishers":["HelloEnjoy"],"package_groups":[],"platforms":{"windows":true,"mac":false,"linux":false},"genres":[{"id":"52","description":"Audio Production"}],"screenshots":[{"id":0,"path_thumbnail":"https:\/\/steamcdn-a.akamaihd.net\/steam\/apps\/624460\/ss_5170d7c30102886ddd9c619a7d261a9e46369650.600x338.jpg?t=1494604209","path_full":"https:\/\/steamcdn-a.akamaihd.net\/steam\/apps\/624460\/ss_5170d7c30102886ddd9c619a7d261a9e46369650.1920x1080.jpg?t=1494604209"},{"id":1,"path_thumbnail":"https:\/\/steamcdn-a.akamaihd.net\/steam\/apps\/624460\/ss_1b538bda53075b1e7f5c9d373da522d3d1bf0bc1.600x338.jpg?t=1494604209","path_full":"https:\/\/steamcdn-a.akamaihd.net\/steam\/apps\/624460\/ss_1b538bda53075b1e7f5c9d373da522d3d1bf0bc1.1920x1080.jpg?t=1494604209"},{"id":2,"path_thumbnail":"https:\/\/steamcdn-a.akamaihd.net\/steam\/apps\/624460\/ss_17420039549ed3be5442bc7aadbd1a846e5b2f34.600x338.jpg?t=1494604209","path_full":"https:\/\/steamcdn-a.akamaihd.net\/steam\/apps\/624460\/ss_17420039549ed3be5442bc7aadbd1a846e5b2f34.1920x1080.jpg?t=1494604209"},{"id":3,"path_thumbnail":"https:\/\/steamcdn-a.akamaihd.net\/steam\/apps\/624460\/ss_30a8a650b80fb8cf10bbd0dce5ff3376abf4cab1.600x338.jpg?t=1494604209","path_full":"https:\/\/steamcdn-a.akamaihd.net\/steam\/apps\/624460\/ss_30a8a650b80fb8cf10bbd0dce5ff3376abf4cab1.1920x1080.jpg?t=1494604209"},{"id":4,"path_thumbnail":"https:\/\/steamcdn-a.akamaihd.net\/steam\/apps\/624460\/ss_7c39932101f3f31f3c66fc715ba7d918fed66962.600x338.jpg?t=1494604209","path_full":"https:\/\/steamcdn-a.akamaihd.net\/steam\/apps\/624460\/ss_7c39932101f3f31f3c66fc715ba7d918fed66962.1920x1080.jpg?t=1494604209"}],"movies":[{"id":256683513,"name":"Fantasynth_1704","thumbnail":"https:\/\/steamcdn-a.akamaihd.net\/steam\/apps\/256683513\/movie.293x165.jpg?t=1492651356","webm":{"480":"http:\/\/steamcdn-a.akamaihd.net\/steam\/apps\/256683513\/movie480.webm?t=1492651356","max":"http:\/\/steamcdn-a.akamaihd.net\/steam\/apps\/256683513\/movie_max.webm?t=1492651356"},"highlight":true}],"release_date":{"coming_soon":false,"date":"Apr 20, 2017"},"support_info":{"url":"http:\/\/fantasynth.com","email":"info@helloenjoy.com"},"background":"https:\/\/steamcdn-a.akamaihd.net\/steam\/apps\/624460\/page_bg_generated_v6b.jpg?t=1494604209"}}}