{"81498":{"success":true,"data":{"type":"movie","name":"Total War: SHOGUN 2 - Fall of the Samurai Announcement ESRB Trailer","steam_appid":81498,"required_age":0,"is_free":false,"detailed_description":"","about_the_game":"","short_description":"","fullgame":{"appid":"201271","name":"Total War: Shogun 2 - Fall of the Samurai"},"header_image":"https:\/\/steamcdn-a.akamaihd.net\/steam\/apps\/81498\/header.jpg?t=1447355573","website":null,"pc_requirements":[],"mac_requirements":[],"linux_requirements":[],"developers":["The Creative Assembly"],"publishers":[""],"package_groups":[],"platforms":{"windows":true,"mac":false,"linux":false},"movies":[{"id":81498,"name":"Total War: SHOGUN 2 - Fall of the Samurai Announcement ESRB Trailer","thumbnail":"https:\/\/steamcdn-a.akamaihd.net\/steam\/apps\/81498\/movie.293x165.jpg?t=1447355573","webm":{"480":"http:\/\/steamcdn-a.akamaihd.net\/steam\/apps\/81498\/movie480.webm?t=1447355573","max":"http:\/\/steamcdn-a.akamaihd.net\/steam\/apps\/81498\/movie_max.webm?t=1447355573"},"highlight":false}],"release_date":{"coming_soon":false,"date":"Mar 23, 2012"},"support_info":{"url":"","email":""},"background":""}}}